realQuadratic.py
realQuadratic-1.0.dist-info/LICENSE
realQuadratic-1.0.dist-info/METADATA
realQuadratic-1.0.dist-info/WHEEL
realQuadratic-1.0.dist-info/top_level.txt
realQuadratic-1.0.dist-info/RECORD
