Metadata-Version: 2.1
Name: realQuadratic
Version: 1.0
Summary: A real, 3 variable professional quadratic equation solver.
Home-page: https://github.com/drewmrk/realQuadratic
Author: Drew Markel
Author-email: drewmrk8@gmail.com
License: MIT
Keywords: math,quadratic,equation,python
Platform: UNKNOWN
Requires-Python: >=3.6.9
